stringsext/__init__.py
stringsext/core.py
stringsext/encoding.py
stringsext/parse.py
stringsext/utils.py
stringsext-0.1.1.dist-info/METADATA
stringsext-0.1.1.dist-info/WHEEL
stringsext-0.1.1.dist-info/top_level.txt
stringsext-0.1.1.dist-info/RECORD
