Metadata-Version: 2.1
Name: stringsext
Version: 0.1.1
Summary: Python subprocess wrapper around the Rust `stringsext` crate.
Requires-Python: >=3.9
